ralfsnbutils/__init__.py
ralfsnbutils/df.py
ralfsnbutils-0.1.0.dist-info/WHEEL
ralfsnbutils-0.1.0.dist-info/METADATA
ralfsnbutils-0.1.0.dist-info/RECORD
