Metadata-Version: 2.1
Name: ralfsnbutils
Version: 0.1.0
Summary: 
Author: rschmidtner
Author-email: RSchmidtner@NewYorker.de
Requires-Python: >=3.6,<4.0
Classifier: Programming Language :: Python :: 3
Classifier: Programming Language :: Python :: 3.6
Classifier: Programming Language :: Python :: 3.7
Classifier: Programming Language :: Python :: 3.8
Classifier: Programming Language :: Python :: 3.9
Requires-Dist: pandas (>=0.23,<0.24)
